rtl/CPU_MEM_1.v
module CPU_MEM_1(
    input wire s,
    input wire enable,
    output reg q);

   always@(posedge enable) begin 
        q <= s;
    end 
endmodule

testbench/CPU_MEM_1_TB.v
`define PATH "sim/CPU_MEM_1_TB_waveform.vcd"
module CPU_MEM_1_TB;

    reg enable;
    reg s;
    wire q;

    // Instantiate the 1-bit memory cell
    CPU_MEM_1 uut (
        .enable(enable),
        .s(s),
        .q(q)
    );
    
    initial begin
        $dumpfile(`PATH);
        $dumpvars(0,CPU_MEM_1_TB);
    end 
    // Clock generation: 10 time units period
    initial begin
        enable = 0;
        forever #5 enable = ~enable;
    end

    // Test stimulus
    initial begin
        // Initialize input
        s = 0;
        
        // Wait for a few clock cycles
        #10;
        
        // Apply test values at each rising clock edge
        s = 1;
        #10;
        s = 0;
        #10;
        s = 1;
        #15; // Wait longer to see output stable
        
        // Finish simulation
        $finish;
    end

    // Optional: monitor signals
    initial begin
        $monitor("At time %t, enable = %b, s = %b, q = %b", $time, enable, s, q);
    end

endmodule

sim/CPU_MEM_1_TB_waveform.vcd
$date
	Fri Oct  3 01:10:30 2025
$end
$version
	Icarus Verilog
$end
$timescale
	1s
$end
$scope module CPU_MEM_1_TB $end
$var wire 1 ! q $end
$var reg 1 " enable $end
$var reg 1 # s $end
$scope module uut $end
$var wire 1 " enable $end
$var wire 1 # s $end
$var reg 1 ! q $end
$upscope $end
$upscope $end
$enddefinitions $end
$comment Show the parameter values. $end
$dumpall
$end
#0
$dumpvars
0#
0"
x!
$end
#5
0!
1"
#10
0"
1#
#15
1!
1"
#20
0"
0#
#25
0!
1"
#30
0"
1#
#35
1!
1"
#40
0"
#45
1"
